{"url":"https:\/\/oauth.bitrix.info\/oauth\/token\/","info":{"url":"https:\/\/oauth.bitrix.info\/oauth\/token\/","content_type":"application\/json","http_code":200,"header_size":361,"request_size":174,"filetime":-1,"ssl_verify_result":0,"redirect_count":0,"total_time":0.362491,"namelookup_time":0.235697,"connect_time":0.245681,"pretransfer_time":0.290454,"size_upload":214,"size_download":449,"speed_download":1240,"speed_upload":591,"download_content_length":-1,"upload_content_length":214,"starttransfer_time":0.290501,"redirect_time":0,"redirect_url":"","primary_ip":"185.86.145.32","certinfo":[],"primary_port":443,"local_ip":"5.101.156.59","local_port":53900},"params":{"this_auth":"Y","params":{"client_id":"local.64612e47178016.84188219","grant_type":"refresh_token","client_secret":"UBkcXpjF0XXl9Z60NNHya53anRVUvVumv9vO0JzNwQ7PMHSsSK","refresh_token":"96bd88640063c54a0063c54600000001000007a7f849d06453d53ae88e08b568641af4"}},"result":{"access_token":"072062640063c54a0063c546000000010000079e771289daa50e4efa4ef2bb3beca46e","expires":1684152327,"expires_in":3600,"scope":"app","domain":"oauth.bitrix.info","server_endpoint":"https:\/\/oauth.bitrix.info\/rest\/","status":"L","client_endpoint":"https:\/\/b24-2dpa92.bitrix24.ru\/rest\/","member_id":"afe0f204fff73733effb7568052115aa","user_id":1,"refresh_token":"f79e89640063c54a0063c546000000010000073c3a53cedae7d4912863061dc78d3119"}}