{"url":"https:\/\/b24-am5g24.bitrix24.ru\/rest\/bizproc.activity.delete.json","info":{"url":"https:\/\/b24-am5g24.bitrix24.ru\/rest\/bizproc.activity.delete.json","content_type":"application\/json; charset=utf-8","http_code":200,"header_size":1187,"request_size":199,"filetime":-1,"ssl_verify_result":0,"redirect_count":0,"total_time":0.203354,"namelookup_time":0.000776,"connect_time":0.019949,"pretransfer_time":0.073905,"size_upload":84,"size_download":275,"speed_download":1354,"speed_upload":413,"download_content_length":-1,"upload_content_length":84,"starttransfer_time":0.073925,"redirect_time":0,"redirect_url":"","primary_ip":"178.132.201.53","certinfo":[],"primary_port":443,"local_ip":"87.236.20.87","local_port":10465},"params":{"method":"bizproc.activity.delete","params":{"CODE":"md5","auth":"4c59456400633acc00633aca00000001000007e232a5ec5c2d698da505e900e0cce77a"}},"result":{"result":true,"time":{"start":1682262846.0236,"finish":1682262846.0771,"duration":0.053550958633423,"processing":0.0047290325164795,"date_start":"2023-04-23T18:14:06+03:00","date_finish":"2023-04-23T18:14:06+03:00","operating_reset_at":1682263446,"operating":0}}}