{"url":"https:\/\/b24-am5g24.bitrix24.ru\/rest\/imbot.message.add.json","info":{"url":"https:\/\/b24-am5g24.bitrix24.ru\/rest\/imbot.message.add.json","content_type":"application\/json; charset=utf-8","http_code":401,"header_size":720,"request_size":194,"filetime":-1,"ssl_verify_result":0,"redirect_count":0,"total_time":129.997262,"namelookup_time":0.001066,"connect_time":129.586917,"pretransfer_time":129.635215,"size_upload":104,"size_download":86,"speed_download":0,"speed_upload":0,"download_content_length":-1,"upload_content_length":104,"starttransfer_time":129.635263,"redirect_time":0,"redirect_url":"","primary_ip":"89.208.228.119","certinfo":[],"primary_port":443,"local_ip":"5.101.156.59","local_port":54944},"params":{"method":"imbot.message.add","params":{"BOT_ID":7,"DIALOG_ID":"","MESSAGE":"","auth":"00f04b6400633ad800633aca00000001000007c0301260ba3e4bcfc3102d64c4357f96"}},"result":{"error":"ACCESS_DENIED","error_description":"REST is available only on commercial plans."}}